charmlibs/pathops/__init__.py
charmlibs/pathops/_constants.py
charmlibs/pathops/_container_path.py
charmlibs/pathops/_errors.py
charmlibs/pathops/_fileinfo.py
charmlibs/pathops/_functions.py
charmlibs/pathops/_local_path.py
charmlibs/pathops/_types.py
charmlibs/pathops/_version.txt
charmlibs/pathops/py.typed
charmlibs_pathops-1.2.0.post0.dist-info/METADATA
charmlibs_pathops-1.2.0.post0.dist-info/WHEEL
charmlibs_pathops-1.2.0.post0.dist-info/top_level.txt
charmlibs_pathops-1.2.0.post0.dist-info/RECORD
