Metadata-Version: 2.4
Name: charmlibs-pathops
Version: 1.2.0.post0
Summary: A pathlib-like interface for Juju K8s charms to interact with files in their workload container.
Author: The Charm Tech team at Canonical Ltd.
Project-URL: Documentation, https://documentation.ubuntu.com/charmlibs/reference/charmlibs/pathops/
Project-URL: Repository, https://github.com/canonical/charmlibs
Project-URL: Issues, https://github.com/canonical/charmlibs/issues
Project-URL: Changelog, https://github.com/canonical/charmlibs/blob/main/pathops/CHANGELOG.md
Classifier: Programming Language :: Python :: 3
Classifier: License :: OSI Approved :: Apache Software License
Classifier: Intended Audience :: Developers
Classifier: Operating System :: POSIX :: Linux
Classifier: Development Status :: 5 - Production/Stable
Requires-Python: >=3.10
Requires-Dist: ops<4,>=2.19
